README.rst
setup.py
cbas/__init__.py
cbas/auth_server.py
cbas/configuration.py
cbas/log.py
cbas/password_providers.py
cbas.egg-info/PKG-INFO
cbas.egg-info/SOURCES.txt
cbas.egg-info/dependency_links.txt
cbas.egg-info/requires.txt
cbas.egg-info/top_level.txt
cbas.egg-info/zip-safe
scripts/cbas