Metadata-Version: 1.1
Name: cbas
Version: 88
Summary: Command line interface to the c-bastion
Home-page: https://github.com/ImmobilienScout24/cbas
Author: Sebastian Spoerer, Valentin Haenel
Author-email: sebastian.spoerer@immobilienscout24.de, valentin.haenel@immobilienscout24.de
License: UNKNOWN
Platform: UNKNOWN
Classifier: Development Status :: 3 - Alpha
Classifier: Programming Language :: Python
